qrconsole/__init__.py
qrconsole/__main__.py
qrconsole/qrconsole.py
qrconsole-1.1.0.dist-info/LICENSE
qrconsole-1.1.0.dist-info/METADATA
qrconsole-1.1.0.dist-info/WHEEL
qrconsole-1.1.0.dist-info/top_level.txt
qrconsole-1.1.0.dist-info/RECORD
