Metadata-Version: 2.1
Name: qrconsole
Version: 1.1.0
Summary: A library to display QR codes in console.
Home-page: https://github.com/MysteryBlokHed/QRConsole
Author: Adam Thompson-Sharpe
Author-email: adamthompsonsharpe@gmail.com
License: UNKNOWN
Platform: UNKNOWN
Classifier: Programming Language :: Python :: 3.6
Classifier: Programming Language :: Python :: 3.7
Classifier: Programming Language :: Python :: 3.8
Classifier: License :: OSI Approved :: MIT License
Classifier: Operating System :: OS Independent
Requires-Python: >=3.6
Requires-Dist: Pillow (>=7.0.0)
